{"type":"FeatureCollection","features":[{"type":"feature","properties":{"country_en":"Pitcairn","name":"Pitcairn Islands","name_adm0":"Pitcairn Islands","name_en":"Pitcairn Islands"},"geometry":{"type":"Point","coordinates":[-128.320312,-24.361459]}}]}