{"type":"FeatureCollection","features":[{"type":"feature","properties":{"country_en":"Sao Tome and Principe","name":"Santo António","name_adm0":"São Tomé e Príncipe","name_adm1":"Principe","name_en":"Santo António"},"geometry":{"type":"Point","coordinates":[7.41783,1.63726]}},{"type":"feature","properties":{"country_en":"Sao Tome and Principe","name":"Sao Tome","name_adm0":"São Tomé e Príncipe","name_adm1":"Sao Tome","name_en":"Sao Tome"},"geometry":{"type":"Point","coordinates":[6.6499999999999995,0.2]}},{"type":"feature","properties":{"country_en":"Sao Tome and Principe","name":"São Tomé","name_adm0":"São Tomé e Príncipe","name_adm1":"Sao Tome","name_en":"Sao Tome"},"geometry":{"type":"Point","coordinates":[6.72732,0.33654]}},{"type":"feature","properties":{"country_en":"Sao Tome and Principe","name":"São Tomé e Príncipe","name_adm0":"São Tomé e Príncipe","name_en":"São Tomé e Príncipe"},"geometry":{"type":"Point","coordinates":[6.619349,0.22031999999999996]}},{"type":"feature","properties":{"country_en":"Sao Tome and Principe","name":"Principe","name_adm0":"São Tomé e Príncipe","name_adm1":"Principe","name_en":"Principe"},"geometry":{"type":"Point","coordinates":[7.41667,1.61667]}}]}