{"type":"FeatureCollection","features":[{"type":"feature","properties":{"country_en":"Tokelau","name":"Atafu","name_adm0":"Tokelau","name_adm1":"Atafu","name_en":"Atafu"},"geometry":{"type":"Point","coordinates":[-172.497,-8.558]}},{"type":"feature","properties":{"country_en":"Tokelau","name":"Nukunonu","name_adm0":"Tokelau","name_adm1":"Nukunonu","name_en":"Nukunonu"},"geometry":{"type":"Point","coordinates":[-171.83,-9.169]}},{"type":"feature","properties":{"country_en":"Tokelau","name":"Fakaofo","name_adm0":"Tokelau","name_adm1":"Fakaofo","name_en":"Fakaofo"},"geometry":{"type":"Point","coordinates":[-171.233,-9.376]}}]}